{
  "lesson_id": 11,
  "lesson_name": "snow-12",
  "subject": "nature",
  "pages_number": 52,
  "pages": [
    {
      "number": 1,
      "url": "",
      "type": 5
    },
    {
      "number": 2,
      "url": "",
      "type": 5
    },
    {
      "number": 3,
      "url": "",
      "type": 1
    },

    {
      "number": 4,
      "url": "",
      "type": null
    },
    {
      "number": 5,
      "url": "",
      "type": null
    },
    {
      "number": 6,
      "url": "",
      "type": null
    },
    {
      "number": 7,
      "url": "",
      "type": null
    },
    {
      "number": 8,
      "url": "",
      "type": null
    },
    {
      "number": 9,
      "url": "",
      "type": null
    },
    {
      "number": 10,
      "url": "",
      "type": null
    },
    {
      "number": 11,
      "url": "",
      "type": 1
    },
    {
      "number": 12,
      "url": "",
      "type": null
    },
    {
      "number": 13,
      "url": "",
      "type": null
    },
    {
      "number": 14,
      "url": "",
      "type": null
    },
    {
      "number": 15,
      "url": "",
      "type": 2
    },
    {
      "number": 16,
      "url": "",
      "type": 1
    },
    {
      "number": 17,
      "url": "",
      "type": null
    },

    {
      "number": 18,
      "url": "",
      "type": null
    },
    {
      "number": "18-1",
      "type": 3
    },
    {
      "number": 19,
      "url": "",
      "type": null
    },
    {
      "number": 20,
      "url": "",
      "type": null
    },
    {
      "number": 21,
      "url": "",
      "type": null
    },
    {
      "number": 22,
      "url": "",
      "type": null
    },

    {
      "number": 23,
      "url": "",
      "type": 2
    },
    {
      "number": 24,
      "url": "",
      "type": null
    },
    {
      "number": 25,
      "url": "",
      "type": null
    },
    {
      "number": "25-1",
      "type": 3
    },
    {
      "number": 26,
      "url": "",
      "type": 2
    },
    {
      "number": 27,
      "url": "",
      "type": 1
    },
    {
      "number": 28,
      "url": "",
      "type": 1
    },
    {
      "number": 29,
      "url": "",
      "type": 2
    },

    {
      "number": 30,
      "url": "",
      "type": 1
    },
    {
      "number": 31,
      "url": "",
      "type": null
    },
    {
      "number": 32,
      "url": "",
      "type": null
    },

    {
      "number": 33,
      "url": "",
      "type": null
    },
    {
      "number": 34,
      "url": "",
      "type": 2
    },

    {
      "number": 35,
      "url": "",
      "type": null
    },
    {
      "number": 36,
      "url": "",
      "type": null
    },
    {
      "number": 37,
      "url": "",
      "type": null
    },
    {
      "number": 38,
      "url": "",
      "type": 1
    },
    {
      "number": 39,
      "url": "",
      "type": null
    },
    {
      "number": 40,
      "url": "",
      "type": 1
    },
    {
      "number": 41,
      "url": "",
      "type": 1
    },
    {
      "number": 42,
      "url": "",
      "type": 1
    },
    {
      "number": 43,
      "url": "",
      "type": 1
    },
    {
      "number": 44,
      "url": "",
      "type": 1
    },
    {
      "number": 45,
      "url": "",
      "type": 1
    },
    {
      "number": 46,
      "url": "",
      "type": null
    },
    {
      "number": 47,
      "url": "",
      "type": null
    },
    {
      "number": 48,
      "url": "",
      "type": 4
    },
    {
      "number": "48-1",
      "type": 3
    },
    {
      "number": 49,
      "url": "",
      "type": 4
    },
    {
      "number": 50,
      "url": "",
      "type": 4
    },
    {
      "number": 51,
      "url": "",
      "type": 1
    },
    {
      "number": 52,
      "url": "",
      "type": 5
    }
  ]
}
